memoorje_crypto/__init__.py
memoorje_crypto/__main__.py
memoorje_crypto/formats.py
memoorje_crypto-0.1.0.dist-info/LICENSE
memoorje_crypto-0.1.0.dist-info/METADATA
memoorje_crypto-0.1.0.dist-info/WHEEL
memoorje_crypto-0.1.0.dist-info/top_level.txt
memoorje_crypto-0.1.0.dist-info/RECORD
