Metadata-Version: 2.1
Name: memoorje-crypto
Version: 0.1.0
Summary: WebCrypto-compatible encryption container formats.
Home-page: https://memoorje.org
Author: memoorje developers
Author-email: tach@memoorje.org
License: MIT
Platform: UNKNOWN
Classifier: Development Status :: 3 - Alpha
Classifier: License :: OSI Approved :: MIT License
Classifier: Programming Language :: Python
Classifier: Programming Language :: Python :: 3 :: Only
Classifier: Topic :: Security :: Cryptography
License-File: LICENSE
Requires-Dist: pycryptodome (~=3.6)
